alicebot/adapter/dingtalk/__init__.py
alicebot/adapter/dingtalk/config.py
alicebot/adapter/dingtalk/event.py
alicebot/adapter/dingtalk/exceptions.py
alicebot/adapter/dingtalk/message.py
alicebot/adapter/dingtalk/py.typed
alicebot_adapter_dingtalk-0.11.0.dist-info/METADATA
alicebot_adapter_dingtalk-0.11.0.dist-info/WHEEL
alicebot_adapter_dingtalk-0.11.0.dist-info/RECORD
